CITATION
CITATION.cff
gammapy/__init__.py
gammapy/__main__.py
gammapy/conftest.py
gammapy/version.py
gammapy/analysis/__init__.py
gammapy/analysis/config.py
gammapy/analysis/core.py
gammapy/analysis/config/docs.yaml
gammapy/analysis/config/example-1d.yaml
gammapy/analysis/config/example-3d.yaml
gammapy/analysis/config/model-1d.yaml
gammapy/analysis/config/model.yaml
gammapy/analysis/tests/__init__.py
gammapy/analysis/tests/test_analysis.py
gammapy/analysis/tests/test_config.py
gammapy/astro/__init__.py
gammapy/astro/darkmatter/__init__.py
gammapy/astro/darkmatter/profiles.py
gammapy/astro/darkmatter/spectra.py
gammapy/astro/darkmatter/utils.py
gammapy/astro/darkmatter/tests/__init__.py
gammapy/astro/darkmatter/tests/test_profiles.py
gammapy/astro/darkmatter/tests/test_spectra.py
gammapy/astro/darkmatter/tests/test_utils.py
gammapy/astro/population/__init__.py
gammapy/astro/population/simulate.py
gammapy/astro/population/spatial.py
gammapy/astro/population/velocity.py
gammapy/astro/population/tests/__init__.py
gammapy/astro/population/tests/test_simulate.py
gammapy/astro/population/tests/test_spatial.py
gammapy/astro/population/tests/test_velocity.py
gammapy/astro/source/__init__.py
gammapy/astro/source/pulsar.py
gammapy/astro/source/pwn.py
gammapy/astro/source/snr.py
gammapy/astro/source/tests/__init__.py
gammapy/astro/source/tests/test_pulsar.py
gammapy/astro/source/tests/test_pwn.py
gammapy/astro/source/tests/test_snr.py
gammapy/catalog/__init__.py
gammapy/catalog/core.py
gammapy/catalog/fermi.py
gammapy/catalog/gammacat.py
gammapy/catalog/hawc.py
gammapy/catalog/hess.py
gammapy/catalog/lhaaso.py
gammapy/catalog/tests/__init__.py
gammapy/catalog/tests/test_core.py
gammapy/catalog/tests/test_fermi.py
gammapy/catalog/tests/test_gammacat.py
gammapy/catalog/tests/test_hawc.py
gammapy/catalog/tests/test_hess.py
gammapy/catalog/tests/test_lhaaso.py
gammapy/catalog/tests/data/2fhl_j0822.6-4250e.txt
gammapy-2.0.1.dist-info/METADATA
gammapy-2.0.1.dist-info/WHEEL
gammapy-2.0.1.dist-info/entry_points.txt
gammapy-2.0.1.dist-info/top_level.txt
gammapy-2.0.1.dist-info/RECORD
gammapy-2.0.1.dist-info/licenses/LICENSE.rst
